Noone/__init__.py
Noone/__version__.py
Noone/base.py
Noone/sd.py
Noone/utils.py
Noone/yolo.py
noone-0.1.1.dist-info/METADATA
noone-0.1.1.dist-info/WHEEL
noone-0.1.1.dist-info/licenses/LICENSE
noone-0.1.1.dist-info/RECORD
