Metadata-Version: 2.1
Name: Noone
Version: 0.1.1
Author-Email: Noone <jungyuko@aift.kr>
License: AGPL-3.0
Project-URL: Repository, https://github.com/jungyuko/noone_pipeline
Requires-Python: >=3.8
Requires-Dist: diffusers[torch]>=0.18.2
Requires-Dist: transformers>=4.25.1
Requires-Dist: ultralytics
